{
  "videoUrl": "https://www.youtube.com/watch?v=SqcY0GlETPk",
  "title": "Demo Video",
  "description": "This is a demo video",
  "category": "Demo",
  "tags": [
    {
      "id": 1,
      "name": "Tag 1"
    },
    {
      "id": 2,
      "name": "Tag 2"
    }
  ],
  "notes": [
    {
      "id": 1,
      "time": "100",
      "note": "This is a note at 1:40",
      "description": "This is a description for the note at 1:40"
    },
    {
      "id": 2,
      "time": "200",
      "note": "This is a note at 3:20",
      "description": "This is a description for the note at 3:20"
    },
    {
      "id": 3,
      "time": "300",
      "note": "This is a note at 5:00",
      "description": "This is a description for the note at 5:00"
    },
    {
    }
  ]
}